{
   "products":[
      {
         "id":"1",
         "name":"Dress Wanita - Hijau",
         "price":"Rp. 350.000,00",
         "image":"http:\/\/www.thoitrangtichtac.com\/productimg\/7000\/6955\/112_Dam_xoe_ren_eo_mau_xanh_a6955.jpg"
      },
      {
         "id":"2",
         "name":"Dress Wanita - Biru Langit",
         "price":"Rp. 350.000,00",
         "image":"http:\/\/www.thoitrangtichtac.com\/productimg\/12000\/11136\/250_Dam_suong_tre_vai_tay_con_don_gian_b1136.jpg"
      },
      {
         "id":"3",
         "name":"Dress Wanita - Brown",
         "price":"Rp. 350.000,00",
         "image":"http:\/\/www.thoitrangtichtac.com\/productimg\/9000\/8598\/29_Dam_len_mau_xam_co_dinh_ngoc_trai_a8598.jpg"
      },
      {
         "id":"4",
         "name":"Dress Wanita - Biru Tua",
         "price":"Rp. 350.000,00",
         "image":"http:\/\/www.thoitrangtichtac.com\/productimg\/9000\/8925\/79_Dam_vintage_xanh_duong_that_no_eo_a8925.jpg"
      },
      {
         "id":"5",
         "name":"Kemeja Pria - Toska",
         "price":"Rp. 175.000,00",
         "image":"http:\/\/www.thoitrangtichtac.com\/productimg\/5000\/4832\/261_Ao_so_mi_ngan_tay_mau_xanh_den_asn015.jpg"
      },
      {
         "id":"6",
         "name":"Kemeja Pria - Abu-abu",
         "price":"Rp. 175.000,00",
         "image":"http:\/\/www.thoitrangtichtac.com\/productimg\/12000\/11047\/6_So_mi_nam_tommy_mau_xam_b1047.jpg"
      },
      {
         "id":"7",
         "name":"Kemeja Pria - Putih",
         "price":"Rp. 175.000,00",
         "image":"http:\/\/www.thoitrangtichtac.com\/productimg\/7000\/6467\/79_Ao_so_mi_nam_tay_ngan_mau_trang_a6467.jpg"
      },
      {
         "id":"8",
         "name":"Sweater Pria",
         "price":"Rp. 250.000,00",
         "image":"http:\/\/www.thoitrangtichtac.com\/productimg\/12000\/11138\/139_Ao_khoac_ni_non_phoi_mau_den_xam_b1138.jpg"
      }
   ]
}
